config_mixin/__init__.py
config_mixin/exceptions.py
config_mixin-1.0.1.dist-info/licenses/LICENSE.txt
config_mixin-1.0.1.dist-info/METADATA
config_mixin-1.0.1.dist-info/WHEEL
config_mixin-1.0.1.dist-info/top_level.txt
config_mixin-1.0.1.dist-info/RECORD
