Metadata-Version: 2.4
Name: config_mixin
Version: 1.0.1
Summary: Provide an auto-discovery process for configurations
Author-email: Stephane Robert <stephane.robert@gmail.com>
License: License :: OSI Approved :: Apache Software License
Project-URL: Homepage, https://github.com/stephanerobert/config-mixin
Classifier: Intended Audience :: Developers
Classifier: Development Status :: 4 - Beta
Classifier: Programming Language :: Python
Classifier: Programming Language :: Python :: 3
Classifier: Programming Language :: Python :: 3 :: Only
Requires-Python: >=3.9
License-File: LICENSE.txt
Requires-Dist: munch
Requires-Dist: PyYAML
Provides-Extra: test
Requires-Dist: pytest; extra == "test"
Requires-Dist: pytest-cov; extra == "test"
Requires-Dist: pyhamcrest; extra == "test"
Dynamic: license-file
